cli/__init__.py
cli/cli.py
cli/command.py
cli/errors.py
create_a_cli-0.0.1.dist-info/LICENSE.txt
create_a_cli-0.0.1.dist-info/METADATA
create_a_cli-0.0.1.dist-info/WHEEL
create_a_cli-0.0.1.dist-info/top_level.txt
create_a_cli-0.0.1.dist-info/RECORD
