Metadata-Version: 2.1
Name: create-a-cli
Version: 0.0.1
Summary: Create command line interfaces using Python
Home-page: https://github.com/Dorukyum/create-a-cli
Author: Dorukyum
License: UNKNOWN
Project-URL: Source, https://github.com/Dorukyum/create-a-cli
Keywords: cli
Platform: UNKNOWN
Classifier: Intended Audience :: Developers
Classifier: License :: OSI Approved :: MIT License
Requires-Python: >=3
License-File: LICENSE.txt
